{"errors":[],"warnings":[],"namedChunkGroups":{"app":{"chunks":[5,2],"assets":["webpack-runtime-722b90b921c9e251ae2c.js","webpack-runtime-722b90b921c9e251ae2c.js.map","app-4746a467374f4b038966.js","app-4746a467374f4b038966.js.map"],"children":{},"childAssets":{}},"component---src-pages-404-js":{"chunks":[0,1,3],"assets":["styles.1b0a15f8938446f7d62f.css","styles-abf832be8cbb5917319b.js","styles-abf832be8cbb5917319b.js.map","1-6da2e14bab9299d7a7f6.js","1-6da2e14bab9299d7a7f6.js.map","component---src-pages-404-js-1f8039f75cc8dceee98f.js","component---src-pages-404-js-1f8039f75cc8dceee98f.js.map"],"children":{},"childAssets":{}},"component---src-pages-index-js":{"chunks":[0,1,4],"assets":["styles.1b0a15f8938446f7d62f.css","styles-abf832be8cbb5917319b.js","styles-abf832be8cbb5917319b.js.map","1-6da2e14bab9299d7a7f6.js","1-6da2e14bab9299d7a7f6.js.map","component---src-pages-index-js-1f1447c2af8513088b87.js","component---src-pages-index-js-1f1447c2af8513088b87.js.map"],"children":{},"childAssets":{}}},"assetsByChunkName":{"app":["webpack-runtime-722b90b921c9e251ae2c.js","app-4746a467374f4b038966.js"],"component---src-pages-404-js":["styles.1b0a15f8938446f7d62f.css","styles-abf832be8cbb5917319b.js","1-6da2e14bab9299d7a7f6.js","component---src-pages-404-js-1f8039f75cc8dceee98f.js"],"component---src-pages-index-js":["styles.1b0a15f8938446f7d62f.css","styles-abf832be8cbb5917319b.js","1-6da2e14bab9299d7a7f6.js","component---src-pages-index-js-1f1447c2af8513088b87.js"]}}